<?xml version="1.0" encoding="UTF-8"?>
<!--
Click nbfs://nbhost/SystemFileSystem/Templates/Licenses/license-default.txt to change this license
Click nbfs://nbhost/SystemFileSystem/Templates/XML/XMLDocument.xml to edit this template
-->

<!DOCTYPE tiles-definitions PUBLIC "-//Apache
Software Foundation//DTD Tiles Configuration 3.0//EN"
"http://tiles.apache.org/dtds/tiles-config_3_0.dtd">
<tiles-definitions>
    
    
    <definition name="baseLayout"
                template="/WEB-INF/layout/base.jsp">
        <put-attribute name="title" value="" />
        <put-attribute name="header"
                       value="/WEB-INF/layout/header.jsp" />
        <put-attribute name="content" value="" />
        <put-attribute name="footer"
                       value="/WEB-INF/layout/footer.jsp" />
    </definition>
    
    
    
    <definition name="baseAdmin"
                template="/WEB-INF/layout/admin/base_admin.jsp">
        <put-attribute name="title" value="" />
        <put-attribute name="header"
                       value="/WEB-INF/layout/admin/header_admin.jsp" />
        <put-attribute name="content" value="" />
        <put-attribute name="footer"
                       value="/WEB-INF/layout/footer.jsp" />
    </definition>
    
    
    
    <definition name="index" extends="baseLayout">
        <put-attribute name="title" value="Cổng thông tin tuyển sinh OU" />
        <put-attribute name="content"
                       value="/WEB-INF/pages/index.jsp" />
    </definition>
    <definition name="department" extends="baseLayout">
        <put-attribute name="title" value="Cổng thông tin tuyển sinh OU"/>
        <put-attribute name="content"
                       value="/WEB-INF/pages/department.jsp" />
    </definition>
    <definition name="department_info" extends="baseLayout">
        <put-attribute name="title" value="Cổng thông tin tuyển sinh OU"/>
        <put-attribute name="content"
                       value="/WEB-INF/pages/department_info.jsp" />
    </definition>
    <definition name="post_index" extends="baseLayout">
        <put-attribute name="title" value="Cổng thông tin tuyển sinh OU"/>
        <put-attribute name="content"
                       value="/WEB-INF/pages/post_index.jsp" />
    </definition>
    <definition name="post_info" extends="baseLayout">
        <put-attribute name="title" value="Cổng thông tin tuyển sinh OU"/>
        <put-attribute name="content"
                       value="/WEB-INF/pages/post_info.jsp" />
    </definition>
    
    <definition name="register" template="/WEB-INF/pages/register.jsp">
    </definition>
    
    <definition name="login" template="/WEB-INF/pages/login.jsp">
    </definition>
    
    
    <definition name="admin" extends="baseAdmin">
        <put-attribute name="title" value="Quản trị OUAdmissions"/>
        <put-attribute name="content"
                       value="/WEB-INF/pages/admin.jsp" />
    </definition>
    
</tiles-definitions>

